{"ProjectBreakpoints":"{\"Value\":{},\"CodeBreakpoints\":{}}","Compiler":"2","ProjectWatches":"{\"Value\":[]}","OpenedDocuments":"[{\"DocumentPath\":\"Udemy_Course/Robot_1.xaml\",\"FactoryId\":\"{ACB8E7BA-F093-44C1-9B50-33ECA51AAE16}\"}]","ProjectActivitiesViewState":"{\"Main.xaml\":[{\"ActivityIdRef\":\"WriteLine_1\",\"IsAdvancedOptionsExpanded\":false,\"Widgets\":{}},{\"ActivityIdRef\":\"InvokeWorkflowFile_2\",\"IsAdvancedOptionsExpanded\":false,\"Categories\":{\"Common\":true,\"Options\":true,\"Log\":true,\"Output\":true},\"Widgets\":{}},{\"ActivityIdRef\":\"WriteLine_3\",\"IsAdvancedOptionsExpanded\":false,\"Widgets\":{}},{\"ActivityIdRef\":\"LogMessage_1\",\"IsAdvancedOptionsExpanded\":false,\"Widgets\":{}},{\"ActivityIdRef\":\"InvokeWorkflowFile_3\",\"IsAdvancedOptionsExpanded\":false,\"Categories\":{\"Common\":true,\"Options\":true,\"Log\":true},\"Widgets\":{}}],\"../../../AppData/Local/Programs/UiPath/Studio/Snippets/Windows/SnippetsCSharp/Samples/Ping Monitor.xaml\":[{\"ActivityIdRef\":\"Delay_1\",\"IsAdvancedOptionsExpanded\":false,\"Widgets\":{}}],\"Workflow.xaml\":[{\"ActivityIdRef\":\"If_1\",\"IsAdvancedOptionsExpanded\":false,\"Widgets\":{}},{\"ActivityIdRef\":\"WriteLine_1\",\"IsAdvancedOptionsExpanded\":false,\"Widgets\":{}},{\"ActivityIdRef\":\"WriteLine_2\",\"IsAdvancedOptionsExpanded\":false,\"Widgets\":{}}],\"Arguments_Demo.xaml\":[],\"Clothing_Consultant.xaml\":[],\"Robot_1_WeatherPreditction.xaml\":[{\"ActivityIdRef\":\"LogMessage_1\",\"IsAdvancedOptionsExpanded\":false,\"Widgets\":{}}],\"UseCase_HyperAutomation/UseCase_1.xaml\":[{\"ActivityIdRef\":\"ForEach`1_1\",\"IsAdvancedOptionsExpanded\":false,\"Categories\":{\"\":true},\"Widgets\":{\"Body\":{\"ShowExpanded\":true}}}]}"}